airflow/providers/apache/spark/__init__.py
airflow/providers/apache/spark/example_dags/__init__.py
airflow/providers/apache/spark/example_dags/example_spark_dag.py
airflow/providers/apache/spark/hooks/__init__.py
airflow/providers/apache/spark/hooks/spark_jdbc.py
airflow/providers/apache/spark/hooks/spark_jdbc_script.py
airflow/providers/apache/spark/hooks/spark_sql.py
airflow/providers/apache/spark/hooks/spark_submit.py
airflow/providers/apache/spark/operators/__init__.py
airflow/providers/apache/spark/operators/spark_jdbc.py
airflow/providers/apache/spark/operators/spark_sql.py
airflow/providers/apache/spark/operators/spark_submit.py
apache_airflow_backport_providers_apache_spark-2021.3.3.dist-info/LICENSE
apache_airflow_backport_providers_apache_spark-2021.3.3.dist-info/METADATA
apache_airflow_backport_providers_apache_spark-2021.3.3.dist-info/NOTICE
apache_airflow_backport_providers_apache_spark-2021.3.3.dist-info/WHEEL
apache_airflow_backport_providers_apache_spark-2021.3.3.dist-info/top_level.txt
apache_airflow_backport_providers_apache_spark-2021.3.3.dist-info/RECORD
